chempleter/.DS_Store
chempleter/__init__.py
chempleter/data/chempleter.ico
chempleter/data/chempleter_logo.png
chempleter/data/itos.json
chempleter/data/model.pt
chempleter/data/stoi.json
chempleter/dataset.py
chempleter/descriptors.py
chempleter/gui.py
chempleter/inference.py
chempleter/model.py
chempleter/processor.py
chempleter/py.typed
chempleter/train.py
chempleter-0.1.0b3.dist-info/licenses/LICENSE
chempleter-0.1.0b3.dist-info/WHEEL
chempleter-0.1.0b3.dist-info/entry_points.txt
chempleter-0.1.0b3.dist-info/METADATA
chempleter-0.1.0b3.dist-info/RECORD
