Metadata-Version: 2.4
Name: chempleter
Version: 0.1.0b3
Summary: A lightweight generative model that extends SMILES fragments into syntactically valid molecules
License-Expression: MIT
License-File: LICENSE
Classifier: License :: OSI Approved :: MIT License
Requires-Dist: nicegui>=3.4.1
Requires-Dist: pandas>=2.3.3
Requires-Dist: pathlib>=1.0.1
Requires-Dist: rdkit>=2025.9.3
Requires-Dist: selfies>=2.2.0
Requires-Dist: torch>=2.9.1
Requires-Dist: torch>=2.9.1 ; extra == 'cpu'
Requires-Dist: torch>=2.9.1 ; extra == 'gpu128'
Requires-Python: >=3.13
Project-URL: Bug Tracker, https://github.com/davistdaniel/chempleter/issues
Project-URL: Documentation, https://github.com/davistdaniel/chempleter
Project-URL: Homepage, https://github.com/davistdaniel/chempleter
Project-URL: Repository, https://github.com/davistdaniel/chempleter
Provides-Extra: cpu
Provides-Extra: gpu128
